email_notifier/__init__.py
email_notifier/exception_notifier.py
email_notifier/general_notifier.py
email_notifier-0.0.1.dist-info/LICENSE
email_notifier-0.0.1.dist-info/METADATA
email_notifier-0.0.1.dist-info/WHEEL
email_notifier-0.0.1.dist-info/top_level.txt
email_notifier-0.0.1.dist-info/RECORD
