Metadata-Version: 2.1
Name: email-notifier
Version: 0.0.1
Summary: A simple email notifier for general messages or exceptions with easy environment configuration
Home-page: https://github.com/sopherapps/email_notifier
Author: Martin Ahindura
Author-email: team.sopherapps@gmail.com
License: MIT
Platform: UNKNOWN
Classifier: License :: OSI Approved :: MIT License
Classifier: Programming Language :: Python :: 3
Classifier: Programming Language :: Python :: 3.6
Requires-Dist: pydantic
